cleverdict/__init__.py
cleverdict/cleverdict.py
cleverdict/test_cleverdict.py
cleverdict-1.7.0.dist-info/LICENSE
cleverdict-1.7.0.dist-info/METADATA
cleverdict-1.7.0.dist-info/WHEEL
cleverdict-1.7.0.dist-info/top_level.txt
cleverdict-1.7.0.dist-info/RECORD
