Metadata-Version: 2.1
Name: cleverdict
Version: 1.7.0
Summary: A data structure which allows both object attributes and dictionary keys and values to be used simultaneously and interchangeably.
Home-page: https://github.com/pfython/cleverdict
Author: Peter Fison
Author-email: peter@southwestlondon.tv
License: MIT
Download-URL: https://github.com/pfython/cleverdict/archive/v_1.7.0.tar.gz
Keywords: data,attribute,key,value,attributes,keys,values,database,utility,tool,clever,dictionary,att,__getattr__,__setattr__,getattr,setattr
Platform: UNKNOWN
Classifier: Development Status :: 5 - Production/Stable
Classifier: Intended Audience :: Developers
Classifier: Topic :: Software Development :: Object Brokering
Classifier: License :: OSI Approved :: MIT License
Classifier: Programming Language :: Python :: 3.2
Classifier: Programming Language :: Python :: 3.3
Classifier: Programming Language :: Python :: 3.4
Classifier: Programming Language :: Python :: 3.5
Classifier: Programming Language :: Python :: 3.6
Classifier: Programming Language :: Python :: 3.7
Classifier: Programming Language :: Python :: 3.8
Classifier: Programming Language :: Python :: 3.9
